paphra_table/__init__.py
paphra_table/__main__.py
paphra_table/table.py
paphra_tktable/__init__.py
paphra_tktable/__main__.py
paphra_tktable/table.py
paphra_tktable-1.0.4.dist-info/LICENSE.txt
paphra_tktable-1.0.4.dist-info/METADATA
paphra_tktable-1.0.4.dist-info/WHEEL
paphra_tktable-1.0.4.dist-info/top_level.txt
paphra_tktable-1.0.4.dist-info/RECORD
