Metadata-Version: 1.1
Name: paphra-tktable
Version: 1.0.4
Summary: Python Tkinter Table. Designed to give the user the control over tables in Python
Home-page: http://github.com/Paphra/PaphraTkTable/
Author: Epaphradito Lugayavu
Author-email: paphra.me@gmail.com
License: LICENSE.txt
Platform: UNKNOWN
Classifier: Programming Language :: Python :: 3
Classifier: Operating System :: OS Independent
